yara_x/__init__.py
yara_x/__init__.pyi
yara_x/py.typed
yara_x/yara_x.abi3.so
yara_x-1.12.0.dist-info/METADATA
yara_x-1.12.0.dist-info/WHEEL
yara_x-1.12.0.dist-info/RECORD
