Metadata-Version: 2.4
Name: yara-x
Version: 1.12.0
Classifier: Programming Language :: Rust
Classifier: Programming Language :: Python :: Implementation :: CPython
Classifier: Programming Language :: Python :: Implementation :: PyPy
Classifier: License :: OSI Approved :: BSD License
Summary: Python bindings for YARA-X
Keywords: pattern-matching,cybersecurity,forensics,malware,yara
Home-Page: https://virustotal.github.io/yara-x
Requires-Python: >=3.9
Project-URL: homepage, https://virustotal.github.io/yara-x
Project-URL: repository, https://github.com/VirusTotal/yara-x.git
